openscm_runner/__init__.py
openscm_runner/adapters/__init__.py
openscm_runner/adapters/base.py
openscm_runner/adapters/ciceroscm_adapter/__init__.py
openscm_runner/adapters/ciceroscm_adapter/_utils.py
openscm_runner/adapters/ciceroscm_adapter/ciceroscm.py
openscm_runner/adapters/ciceroscm_adapter/ciceroscm_wrapper.py
openscm_runner/adapters/ciceroscm_adapter/make_scenario_files.py
openscm_runner/adapters/ciceroscm_adapter/read_results.py
openscm_runner/adapters/ciceroscm_adapter/utils_templates/gases_v1RCMIP.txt
openscm_runner/adapters/ciceroscm_adapter/utils_templates/pam_RCMIP_test_klimsensdefault.scm
openscm_runner/adapters/ciceroscm_adapter/utils_templates/run_dir/gases_v1RCMIP.txt
openscm_runner/adapters/ciceroscm_adapter/utils_templates/run_dir/input_OTHER/NATEMIS/natemis_ch4.txt
openscm_runner/adapters/ciceroscm_adapter/utils_templates/run_dir/input_OTHER/NATEMIS/natemis_n2o.txt
openscm_runner/adapters/ciceroscm_adapter/utils_templates/run_dir/input_RF/RFLUC/IPCC_LUCalbedo.txt
openscm_runner/adapters/ciceroscm_adapter/utils_templates/run_dir/input_RF/RFSUN/solar_IPCC.txt
openscm_runner/adapters/ciceroscm_adapter/utils_templates/run_dir/input_RF/RFVOLC/meanVOLCmnd_ipcc_NH.txt
openscm_runner/adapters/ciceroscm_adapter/utils_templates/run_dir/input_RF/RFVOLC/meanVOLCmnd_ipcc_SH.txt
openscm_runner/adapters/ciceroscm_adapter/utils_templates/run_dir/scm_vCH4fb_bfx
openscm_runner/adapters/ciceroscm_adapter/utils_templates/run_dir/scm_vCH4fb_bfx.exe
openscm_runner/adapters/ciceroscm_adapter/utils_templates/run_dir/ssp245_conc_RCMIP.txt
openscm_runner/adapters/ciceroscm_adapter/utils_templates/ssp245_em_RCMIP.txt
openscm_runner/adapters/ciceroscm_adapter/write_parameter_files.py
openscm_runner/adapters/ciceroscm_py_adapter/__init__.py
openscm_runner/adapters/ciceroscm_py_adapter/_compat.py
openscm_runner/adapters/ciceroscm_py_adapter/ciceroscmpy.py
openscm_runner/adapters/ciceroscm_py_adapter/cscmpy_wrapper.py
openscm_runner-0.13.0.dist-info/LICENSE
openscm_runner-0.13.0.dist-info/METADATA
openscm_runner-0.13.0.dist-info/WHEEL
openscm_runner-0.13.0.dist-info/RECORD
