Metadata-Version: 2.1
Name: openscm-runner
Version: 0.13.0
Summary: Thin wrapper to run emissions scenarios with simple climate models
Home-page: https://github.com/openscm/openscm-runner
License: BSD-3-Clause
Keywords: openscm,runner,python,simple,climate,model
Author: Zebedee Nicholls
Author-email: zebedee.nicholls@climate-energy-college.org
Requires-Python: >=3.9,<4.0
Classifier: Development Status :: 4 - Beta
Classifier: Intended Audience :: Developers
Classifier: Intended Audience :: Science/Research
Classifier: License :: OSI Approved :: BSD License
Classifier: Operating System :: OS Independent
Classifier: Programming Language :: Python
Classifier: Programming Language :: Python :: 3
Classifier: Programming Language :: Python :: 3.9
Classifier: Programming Language :: Python :: 3.10
Classifier: Programming Language :: Python :: 3.11
Classifier: Programming Language :: Python :: 3.12
Classifier: Topic :: Scientific/Engineering
Provides-Extra: ciceroscmpy
Provides-Extra: fair
Provides-Extra: magicc
Provides-Extra: models
Provides-Extra: notebooks
Requires-Dist: ciceroscm (==1.1.1) ; extra == "ciceroscmpy" or extra == "models"
Requires-Dist: fair (<2) ; extra == "fair" or extra == "models"
Requires-Dist: ipywidgets (>=8.1.1,<9.0.0) ; extra == "notebooks"
Requires-Dist: notebook ; extra == "notebooks"
Requires-Dist: openscm-units (>=0.5.0)
Requires-Dist: pymagicc (<3) ; extra == "magicc" or extra == "models"
Requires-Dist: python-dotenv (>=1.0.0,<2.0.0)
Requires-Dist: scmdata (>=0.7.4)
Requires-Dist: seaborn (>=0.13.1,<0.14.0) ; extra == "notebooks"
Requires-Dist: tqdm (>=4.66.1,<5.0.0)
Project-URL: Repository, https://github.com/openscm/openscm-runner
